README.md
setup.cfg
setup.py
django_pass_strength_validator/__init__.py
django_pass_strength_validator/validator.py
django_pass_strength_validator.egg-info/PKG-INFO
django_pass_strength_validator.egg-info/SOURCES.txt
django_pass_strength_validator.egg-info/dependency_links.txt
django_pass_strength_validator.egg-info/requires.txt
django_pass_strength_validator.egg-info/top_level.txt