Metadata-Version: 2.1
Name: django-pass-strength-validator
Version: 1.0.0
Summary: UNKNOWN
Home-page: https://github.com/mfdeux/django-pass-strength-validator
Author: Marc Ford
Author-email: mrfxyz567@gmail.com
License: MIT
Keywords: django,zxcvbn,password,security
Platform: UNKNOWN
Classifier: Intended Audience :: Developers
Classifier: License :: OSI Approved :: MIT License
Classifier: Natural Language :: English
Classifier: Programming Language :: Python :: 3.5
Classifier: Programming Language :: Python :: 3.6
Classifier: Programming Language :: Python :: 3.7
Classifier: Topic :: Security
Classifier: Topic :: Software Development :: Libraries :: Python Modules
